README.md
setup.cfg
setup.py
rangev2/__init__.py
rangev2/new_range.py
rangev2.egg-info/PKG-INFO
rangev2.egg-info/SOURCES.txt
rangev2.egg-info/dependency_links.txt
rangev2.egg-info/top_level.txt