Metadata-Version: 2.1
Name: rangev2
Version: 0.1.1
Summary: A new version of python range
Home-page: https://github.com/co18326/rangev2
Author: Ishan Gambhir
Author-email: ishugambhir2001@gmail.com
License: MIT
Download-URL: https://github.com/CO18326/rangev2/archive/V_0.1.1.tar.gz
Keywords: range,latest,beginer,library,gp,agp
Platform: UNKNOWN
Classifier: Development Status :: 5 - Production/Stable
Classifier: Intended Audience :: Developers
Classifier: Topic :: Software Development :: Build Tools
Classifier: License :: OSI Approved :: MIT License
Classifier: Programming Language :: Python :: 3
Classifier: Programming Language :: Python :: 3.4
Classifier: Programming Language :: Python :: 3.5
Classifier: Programming Language :: Python :: 3.6
Classifier: Programming Language :: Python :: 3.7
Classifier: Programming Language :: Python :: 3.8
